swarmauri_mre_crypto_keyring/KeyringMreCrypto.py
swarmauri_mre_crypto_keyring/__init__.py
swarmauri_mre_crypto_keyring-0.3.0.dev4.dist-info/LICENSE
swarmauri_mre_crypto_keyring-0.3.0.dev4.dist-info/METADATA
swarmauri_mre_crypto_keyring-0.3.0.dev4.dist-info/WHEEL
swarmauri_mre_crypto_keyring-0.3.0.dev4.dist-info/entry_points.txt
swarmauri_mre_crypto_keyring-0.3.0.dev4.dist-info/RECORD
